[{"family":"MaterialIcons","fonts":[{"asset":"fonts/MaterialIcons-Regular.otf"}]},{"family":"Rouna","fonts":[{"asset":"fonts/Rouna-Regular.otf"},{"style":"italic","asset":"fonts/Rouna-RegularItalic.otf"},{"weight":500,"asset":"fonts/Rouna-Medium.otf"},{"weight":400,"style":"italic","asset":"fonts/Rouna-MediumItalic.otf"},{"weight":700,"asset":"fonts/Rouna-Bold.otf"},{"weight":700,"style":"italic","asset":"fonts/Rouna-BoldItalic.otf"}]},{"family":"packages/cupertino_icons/CupertinoIcons","fonts":[{"asset":"packages/cupertino_icons/assets/CupertinoIcons.ttf"}]}]